tdb.py
tdb_py-0.9.5.dist-info/LICENSE
tdb_py-0.9.5.dist-info/METADATA
tdb_py-0.9.5.dist-info/WHEEL
tdb_py-0.9.5.dist-info/top_level.txt
tdb_py-0.9.5.dist-info/RECORD
