Metadata-Version: 2.1
Name: tdb-py
Version: 0.9.5
Summary: A pure Python library supporting Tdb “Text DataBase” format, a plain text human readable typed database storage format superior to CSV.
Home-page: https://github.com/mark-summerfield/tdb-py
Author: Mark Summerfield
Author-email: mark@qtrac.eu
License: GPLv3
Platform: UNKNOWN
Classifier: Development Status :: 5 - Production/Stable
Classifier: Intended Audience :: Developers
Classifier: License :: OSI Approved :: GNU General Public License v3 (GPLv3)
Classifier: Programming Language :: Python :: 3
Classifier: Programming Language :: Python :: 3.8
Classifier: Topic :: Software Development :: Libraries
Requires-Python: >=3.8
Requires-Dist: editabletuple
